{"nodes": [{"id": "e_git_solucoes_urbanas_api_go_internal_repository_system_notification_repository_go", "label": "system_notification_repository.go", "file_type": "code", "source_file": "E:\\git\\solucoes-urbanas-api-go\\internal\\repository\\system_notification_repository.go", "source_location": "L1"}, {"id": "repository_systemnotificationrepository", "label": "SystemNotificationRepository", "file_type": "code", "source_file": "E:\\git\\solucoes-urbanas-api-go\\internal\\repository\\system_notification_repository.go", "source_location": "L11"}, {"id": "repository_system_notification_repository_newsystemnotificationrepository", "label": "NewSystemNotificationRepository()", "file_type": "code", "source_file": "E:\\git\\solucoes-urbanas-api-go\\internal\\repository\\system_notification_repository.go", "source_location": "L15"}, {"id": "repository_systemnotificationrepository_create", "label": ".Create()", "file_type": "code", "source_file": "E:\\git\\solucoes-urbanas-api-go\\internal\\repository\\system_notification_repository.go", "source_location": "L19"}, {"id": "repository_systemnotificationrepository_list", "label": ".List()", "file_type": "code", "source_file": "E:\\git\\solucoes-urbanas-api-go\\internal\\repository\\system_notification_repository.go", "source_location": "L33"}, {"id": "repository_systemnotificationrepository_getbyid", "label": ".GetByID()", "file_type": "code", "source_file": "E:\\git\\solucoes-urbanas-api-go\\internal\\repository\\system_notification_repository.go", "source_location": "L86"}, {"id": "repository_systemnotificationrepository_update", "label": ".Update()", "file_type": "code", "source_file": "E:\\git\\solucoes-urbanas-api-go\\internal\\repository\\system_notification_repository.go", "source_location": "L97"}, {"id": "repository_systemnotificationrepository_markasread", "label": ".MarkAsRead()", "file_type": "code", "source_file": "E:\\git\\solucoes-urbanas-api-go\\internal\\repository\\system_notification_repository.go", "source_location": "L124"}, {"id": "repository_systemnotificationrepository_delete", "label": ".Delete()", "file_type": "code", "source_file": "E:\\git\\solucoes-urbanas-api-go\\internal\\repository\\system_notification_repository.go", "source_location": "L139"}], "edges": [{"source": "e_git_solucoes_urbanas_api_go_internal_repository_system_notification_repository_go", "target": "go_pkg_context", "relation": "imports_from", "confidence": "EXTRACTED", "source_file": "E:\\git\\solucoes-urbanas-api-go\\internal\\repository\\system_notification_repository.go", "source_location": "L4", "weight": 1.0, "context": "import"}, {"source": "e_git_solucoes_urbanas_api_go_internal_repository_system_notification_repository_go", "target": "go_pkg_fmt", "relation": "imports_from", "confidence": "EXTRACTED", "source_file": "E:\\git\\solucoes-urbanas-api-go\\internal\\repository\\system_notification_repository.go", "source_location": "L5", "weight": 1.0, "context": "import"}, {"source": "e_git_solucoes_urbanas_api_go_internal_repository_system_notification_repository_go", "target": "go_pkg_github_com_jackc_pgx_v5_pgxpool", "relation": "imports_from", "confidence": "EXTRACTED", "source_file": "E:\\git\\solucoes-urbanas-api-go\\internal\\repository\\system_notification_repository.go", "source_location": "L7", "weight": 1.0, "context": "import"}, {"source": "e_git_solucoes_urbanas_api_go_internal_repository_system_notification_repository_go", "target": "go_pkg_github_com_laiirton_solucoes_urbanas_api_internal_models", "relation": "imports_from", "confidence": "EXTRACTED", "source_file": "E:\\git\\solucoes-urbanas-api-go\\internal\\repository\\system_notification_repository.go", "source_location": "L8", "weight": 1.0, "context": "import"}, {"source": "e_git_solucoes_urbanas_api_go_internal_repository_system_notification_repository_go", "target": "repository_systemnotificationrepository", "relation": "contains", "confidence": "EXTRACTED", "source_file": "E:\\git\\solucoes-urbanas-api-go\\internal\\repository\\system_notification_repository.go", "source_location": "L11", "weight": 1.0}, {"source": "e_git_solucoes_urbanas_api_go_internal_repository_system_notification_repository_go", "target": "repository_system_notification_repository_newsystemnotificationrepository", "relation": "contains", "confidence": "EXTRACTED", "source_file": "E:\\git\\solucoes-urbanas-api-go\\internal\\repository\\system_notification_repository.go", "source_location": "L15", "weight": 1.0}, {"source": "repository_systemnotificationrepository", "target": "repository_systemnotificationrepository_create", "relation": "method", "confidence": "EXTRACTED", "source_file": "E:\\git\\solucoes-urbanas-api-go\\internal\\repository\\system_notification_repository.go", "source_location": "L19", "weight": 1.0}, {"source": "repository_systemnotificationrepository", "target": "repository_systemnotificationrepository_list", "relation": "method", "confidence": "EXTRACTED", "source_file": "E:\\git\\solucoes-urbanas-api-go\\internal\\repository\\system_notification_repository.go", "source_location": "L33", "weight": 1.0}, {"source": "repository_systemnotificationrepository", "target": "repository_systemnotificationrepository_getbyid", "relation": "method", "confidence": "EXTRACTED", "source_file": "E:\\git\\solucoes-urbanas-api-go\\internal\\repository\\system_notification_repository.go", "source_location": "L86", "weight": 1.0}, {"source": "repository_systemnotificationrepository", "target": "repository_systemnotificationrepository_update", "relation": "method", "confidence": "EXTRACTED", "source_file": "E:\\git\\solucoes-urbanas-api-go\\internal\\repository\\system_notification_repository.go", "source_location": "L97", "weight": 1.0}, {"source": "repository_systemnotificationrepository", "target": "repository_systemnotificationrepository_markasread", "relation": "method", "confidence": "EXTRACTED", "source_file": "E:\\git\\solucoes-urbanas-api-go\\internal\\repository\\system_notification_repository.go", "source_location": "L124", "weight": 1.0}, {"source": "repository_systemnotificationrepository", "target": "repository_systemnotificationrepository_delete", "relation": "method", "confidence": "EXTRACTED", "source_file": "E:\\git\\solucoes-urbanas-api-go\\internal\\repository\\system_notification_repository.go", "source_location": "L139", "weight": 1.0}], "raw_calls": [{"caller_nid": "repository_systemnotificationrepository_create", "callee": "Scan", "is_member_call": true, "source_file": "E:\\git\\solucoes-urbanas-api-go\\internal\\repository\\system_notification_repository.go", "source_location": "L25"}, {"caller_nid": "repository_systemnotificationrepository_create", "callee": "QueryRow", "is_member_call": true, "source_file": "E:\\git\\solucoes-urbanas-api-go\\internal\\repository\\system_notification_repository.go", "source_location": "L25"}, {"caller_nid": "repository_systemnotificationrepository_create", "callee": "Errorf", "is_member_call": false, "source_file": "E:\\git\\solucoes-urbanas-api-go\\internal\\repository\\system_notification_repository.go", "source_location": "L28"}, {"caller_nid": "repository_systemnotificationrepository_list", "callee": "append", "is_member_call": false, "source_file": "E:\\git\\solucoes-urbanas-api-go\\internal\\repository\\system_notification_repository.go", "source_location": "L42"}, {"caller_nid": "repository_systemnotificationrepository_list", "callee": "Sprintf", "is_member_call": false, "source_file": "E:\\git\\solucoes-urbanas-api-go\\internal\\repository\\system_notification_repository.go", "source_location": "L48"}, {"caller_nid": "repository_systemnotificationrepository_list", "callee": "len", "is_member_call": false, "source_file": "E:\\git\\solucoes-urbanas-api-go\\internal\\repository\\system_notification_repository.go", "source_location": "L48"}, {"caller_nid": "repository_systemnotificationrepository_list", "callee": "append", "is_member_call": false, "source_file": "E:\\git\\solucoes-urbanas-api-go\\internal\\repository\\system_notification_repository.go", "source_location": "L52"}, {"caller_nid": "repository_systemnotificationrepository_list", "callee": "Sprintf", "is_member_call": false, "source_file": "E:\\git\\solucoes-urbanas-api-go\\internal\\repository\\system_notification_repository.go", "source_location": "L65"}, {"caller_nid": "repository_systemnotificationrepository_list", "callee": "len", "is_member_call": false, "source_file": "E:\\git\\solucoes-urbanas-api-go\\internal\\repository\\system_notification_repository.go", "source_location": "L65"}, {"caller_nid": "repository_systemnotificationrepository_list", "callee": "len", "is_member_call": false, "source_file": "E:\\git\\solucoes-urbanas-api-go\\internal\\repository\\system_notification_repository.go", "source_location": "L65"}, {"caller_nid": "repository_systemnotificationrepository_list", "callee": "append", "is_member_call": false, "source_file": "E:\\git\\solucoes-urbanas-api-go\\internal\\repository\\system_notification_repository.go", "source_location": "L66"}, {"caller_nid": "repository_systemnotificationrepository_list", "callee": "Query", "is_member_call": true, "source_file": "E:\\git\\solucoes-urbanas-api-go\\internal\\repository\\system_notification_repository.go", "source_location": "L68"}, {"caller_nid": "repository_systemnotificationrepository_list", "callee": "Errorf", "is_member_call": false, "source_file": "E:\\git\\solucoes-urbanas-api-go\\internal\\repository\\system_notification_repository.go", "source_location": "L70"}, {"caller_nid": "repository_systemnotificationrepository_list", "callee": "Close", "is_member_call": true, "source_file": "E:\\git\\solucoes-urbanas-api-go\\internal\\repository\\system_notification_repository.go", "source_location": "L72"}, {"caller_nid": "repository_systemnotificationrepository_list", "callee": "Next", "is_member_call": true, "source_file": "E:\\git\\solucoes-urbanas-api-go\\internal\\repository\\system_notification_repository.go", "source_location": "L75"}, {"caller_nid": "repository_systemnotificationrepository_list", "callee": "Scan", "is_member_call": true, "source_file": "E:\\git\\solucoes-urbanas-api-go\\internal\\repository\\system_notification_repository.go", "source_location": "L77"}, {"caller_nid": "repository_systemnotificationrepository_list", "callee": "Errorf", "is_member_call": false, "source_file": "E:\\git\\solucoes-urbanas-api-go\\internal\\repository\\system_notification_repository.go", "source_location": "L78"}, {"caller_nid": "repository_systemnotificationrepository_list", "callee": "append", "is_member_call": false, "source_file": "E:\\git\\solucoes-urbanas-api-go\\internal\\repository\\system_notification_repository.go", "source_location": "L80"}, {"caller_nid": "repository_systemnotificationrepository_getbyid", "callee": "Scan", "is_member_call": true, "source_file": "E:\\git\\solucoes-urbanas-api-go\\internal\\repository\\system_notification_repository.go", "source_location": "L89"}, {"caller_nid": "repository_systemnotificationrepository_getbyid", "callee": "QueryRow", "is_member_call": true, "source_file": "E:\\git\\solucoes-urbanas-api-go\\internal\\repository\\system_notification_repository.go", "source_location": "L89"}, {"caller_nid": "repository_systemnotificationrepository_getbyid", "callee": "Errorf", "is_member_call": false, "source_file": "E:\\git\\solucoes-urbanas-api-go\\internal\\repository\\system_notification_repository.go", "source_location": "L92"}, {"caller_nid": "repository_systemnotificationrepository_update", "callee": "Scan", "is_member_call": true, "source_file": "E:\\git\\solucoes-urbanas-api-go\\internal\\repository\\system_notification_repository.go", "source_location": "L110"}, {"caller_nid": "repository_systemnotificationrepository_update", "callee": "QueryRow", "is_member_call": true, "source_file": "E:\\git\\solucoes-urbanas-api-go\\internal\\repository\\system_notification_repository.go", "source_location": "L110"}, {"caller_nid": "repository_systemnotificationrepository_update", "callee": "nullableValue", "is_member_call": false, "source_file": "E:\\git\\solucoes-urbanas-api-go\\internal\\repository\\system_notification_repository.go", "source_location": "L111"}, {"caller_nid": "repository_systemnotificationrepository_update", "callee": "nullableValue", "is_member_call": false, "source_file": "E:\\git\\solucoes-urbanas-api-go\\internal\\repository\\system_notification_repository.go", "source_location": "L112"}, {"caller_nid": "repository_systemnotificationrepository_update", "callee": "nullableValue", "is_member_call": false, "source_file": "E:\\git\\solucoes-urbanas-api-go\\internal\\repository\\system_notification_repository.go", "source_location": "L113"}, {"caller_nid": "repository_systemnotificationrepository_update", "callee": "nullableValue", "is_member_call": false, "source_file": "E:\\git\\solucoes-urbanas-api-go\\internal\\repository\\system_notification_repository.go", "source_location": "L114"}, {"caller_nid": "repository_systemnotificationrepository_update", "callee": "nullableValue", "is_member_call": false, "source_file": "E:\\git\\solucoes-urbanas-api-go\\internal\\repository\\system_notification_repository.go", "source_location": "L115"}, {"caller_nid": "repository_systemnotificationrepository_update", "callee": "Errorf", "is_member_call": false, "source_file": "E:\\git\\solucoes-urbanas-api-go\\internal\\repository\\system_notification_repository.go", "source_location": "L119"}, {"caller_nid": "repository_systemnotificationrepository_markasread", "callee": "Scan", "is_member_call": true, "source_file": "E:\\git\\solucoes-urbanas-api-go\\internal\\repository\\system_notification_repository.go", "source_location": "L131"}, {"caller_nid": "repository_systemnotificationrepository_markasread", "callee": "QueryRow", "is_member_call": true, "source_file": "E:\\git\\solucoes-urbanas-api-go\\internal\\repository\\system_notification_repository.go", "source_location": "L131"}, {"caller_nid": "repository_systemnotificationrepository_markasread", "callee": "Errorf", "is_member_call": false, "source_file": "E:\\git\\solucoes-urbanas-api-go\\internal\\repository\\system_notification_repository.go", "source_location": "L134"}, {"caller_nid": "repository_systemnotificationrepository_delete", "callee": "Exec", "is_member_call": true, "source_file": "E:\\git\\solucoes-urbanas-api-go\\internal\\repository\\system_notification_repository.go", "source_location": "L141"}, {"caller_nid": "repository_systemnotificationrepository_delete", "callee": "Errorf", "is_member_call": false, "source_file": "E:\\git\\solucoes-urbanas-api-go\\internal\\repository\\system_notification_repository.go", "source_location": "L143"}, {"caller_nid": "repository_systemnotificationrepository_delete", "callee": "RowsAffected", "is_member_call": true, "source_file": "E:\\git\\solucoes-urbanas-api-go\\internal\\repository\\system_notification_repository.go", "source_location": "L145"}, {"caller_nid": "repository_systemnotificationrepository_delete", "callee": "Errorf", "is_member_call": false, "source_file": "E:\\git\\solucoes-urbanas-api-go\\internal\\repository\\system_notification_repository.go", "source_location": "L146"}]}